{
  "date": "2026-06-28",
  "signals": {
    "mvrv_zscore": {
      "raw": -0.3463761452283227,
      "score": 50,
      "sell_score": 0,
      "as_of": "2026-06-28"
    },
    "ma_200w": {
      "raw": 0.953565223229678,
      "score": 100,
      "sell_score": 0,
      "as_of": "2026-06-28"
    },
    "monthly_rsi": {
      "raw": 47.28781103574178,
      "score": 50,
      "sell_score": 0,
      "as_of": "2026-05-31"
    },
    "pi_cycle": {
      "raw": 0.3966323947034778,
      "score": 100,
      "sell_score": 0,
      "as_of": "2026-06-28"
    },
    "puell": {
      "raw": 0.6506113509447227,
      "score": 50,
      "sell_score": 0,
      "as_of": "2026-06-28"
    },
    "fear_greed": {
      "raw": 18.0,
      "score": 100,
      "sell_score": 0,
      "as_of": "2026-06-28"
    }
  }
}